Compiled from "HelloJava.java"
public class HelloJava {
  public HelloJava();
    Code:
       0: aload_0
       1: invokespecial #1                  // Method java/lang/Object."<init>":()V
       4: return
    LineNumberTable:
      line 1: 0
    LocalVariableTable:
      Start  Length  Slot  Name   Signature
          0       5     0  this   LHelloJava;

  public static void main(java.lang.String[]);
    Code:
       0: iconst_1
       1: istore_1
       2: iconst_2
       3: istore_2
       4: iload_1
       5: i2d
       6: iload_2
       7: i2d
       8: ddiv
       9: dstore_3
      10: return
    LineNumberTable:
      line 5: 0
      line 6: 2
      line 7: 4
      line 8: 10
    LocalVariableTable:
      Start  Length  Slot  Name   Signature
          0      11     0  args   [Ljava/lang/String;
          2       9     1     a   I
          4       7     2     b   I
         10       1     3     c   D
}
